bubble_aide/__init__.py
bubble_aide/bubble.py
bubble_aide/bubbleL2.py
bubble_aide/delegate.py
bubble_aide/govern.py
bubble_aide/main.py
bubble_aide/restricting.py
bubble_aide/reward.py
bubble_aide/slashing.py
bubble_aide/staking.py
bubble_aide/stakingL2.py
bubble_aide/temp_prikey.py
bubble_aide/abc/__init__.py
bubble_aide/abc/module.py
bubble_aide/statics/__init__.py
bubble_aide/statics/calculator.py
bubble_aide/statics/constant.py
bubble_aide/statics/contract.py
bubble_aide/statics/economic.py
bubble_aide/statics/graphqls.py
bubble_aide/utils/__init__.py
bubble_aide/utils/utils.py
bubble_aide/utils/wrapper.py
bubble_aide-2.1.7.dist-info/LICENSE
bubble_aide-2.1.7.dist-info/METADATA
bubble_aide-2.1.7.dist-info/WHEEL
bubble_aide-2.1.7.dist-info/top_level.txt
bubble_aide-2.1.7.dist-info/RECORD
