Metadata-Version: 2.1
Name: bubble-aide
Version: 2.1.7
Summary: bubble aide
Home-page: https://github.com/shinnng/bubble-aide
Author: Shing
Author-email: shinnng@outlook.com
License: MIT
Keywords: bubble-aide
Platform: UNKNOWN
Classifier: Development Status :: 4 - Beta
Classifier: Intended Audience :: Developers
Classifier: License :: OSI Approved :: MIT License
Classifier: Natural Language :: English
Classifier: Programming Language :: Python :: 3
Classifier: Programming Language :: Python :: 3.8
Classifier: Programming Language :: Python :: 3.9
Classifier: Programming Language :: Python :: 3.10
Classifier: Programming Language :: Python :: 3.11
Requires-Dist: bubble-sdk >=0.1.0
Provides-Extra: bubble-aide
Requires-Dist: bubble.py >=0.1.0 ; extra == 'bubble-aide'
Requires-Dist: eth-account >=0.8.0 ; extra == 'bubble-aide'
Requires-Dist: eth-hash >=0.5.1 ; extra == 'bubble-aide'
Requires-Dist: eth-keys >=0.4.0 ; extra == 'bubble-aide'
Requires-Dist: eth-typing >=3.0.0 ; extra == 'bubble-aide'
Requires-Dist: eth-utils >=2.1.0 ; extra == 'bubble-aide'
Requires-Dist: rlp >=3.0.0 ; extra == 'bubble-aide'
Requires-Dist: gql >=3.0.0rc0 ; extra == 'bubble-aide'
